[
    {
        "key": "group_5bb50f028546b",
        "title": "Portfolio Fields",
        "fields": [
            {
                "key": "field_5bb564d62ce6f",
                "label": "Introduction",
                "name": "introduction",
                "type": "wysiwyg",
                "instructions": "This is the main content that shows before the other fields.",
                "required": 0,
                "conditional_logic": 0,
                "wrapper": {
                    "width": "",
                    "class": "",
                    "id": ""
                },
                "default_value": "",
                "tabs": "all",
                "toolbar": "full",
                "media_upload": 1,
                "delay": 0
            },
            {
                "key": "field_5bb5117777d8b",
                "label": "Skills Used",
                "name": "skills_used",
                "type": "text",
                "instructions": "",
                "required": 0,
                "conditional_logic": 0,
                "wrapper": {
                    "width": "",
                    "class": "",
                    "id": ""
                },
                "default_value": "",
                "placeholder": "",
                "prepend": "",
                "append": "",
                "maxlength": ""
            },
            {
                "key": "field_5bb5118c77d8c",
                "label": "Materials",
                "name": "materials",
                "type": "text",
                "instructions": "",
                "required": 0,
                "conditional_logic": 0,
                "wrapper": {
                    "width": "",
                    "class": "",
                    "id": ""
                },
                "default_value": "",
                "placeholder": "",
                "prepend": "",
                "append": "",
                "maxlength": ""
            },
            {
                "key": "field_5bb5639b71547",
                "label": "Challenges",
                "name": "challenges",
                "type": "text",
                "instructions": "",
                "required": 0,
                "conditional_logic": 0,
                "wrapper": {
                    "width": "",
                    "class": "",
                    "id": ""
                },
                "default_value": "",
                "placeholder": "",
                "prepend": "",
                "append": "",
                "maxlength": ""
            },
            {
                "key": "field_5bb563a671548",
                "label": "Lessons Learned",
                "name": "lessons_learned",
                "type": "text",
                "instructions": "",
                "required": 0,
                "conditional_logic": 0,
                "wrapper": {
                    "width": "",
                    "class": "",
                    "id": ""
                },
                "default_value": "",
                "placeholder": "",
                "prepend": "",
                "append": "",
                "maxlength": ""
            },
            {
                "key": "field_5bb5113c77d8a",
                "label": "Client",
                "name": "client",
                "type": "text",
                "instructions": "",
                "required": 0,
                "conditional_logic": 0,
                "wrapper": {
                    "width": "",
                    "class": "",
                    "id": ""
                },
                "default_value": "",
                "placeholder": "",
                "prepend": "",
                "append": "",
                "maxlength": ""
            }
        ],
        "location": [
            [
                {
                    "param": "post_type",
                    "operator": "==",
                    "value": "portfolio"
                }
            ]
        ],
        "menu_order": 0,
        "position": "acf_after_title",
        "style": "default",
        "label_placement": "top",
        "instruction_placement": "label",
        "hide_on_screen": "",
        "active": 1,
        "description": ""
    }
]